{
  "rasa_nlu_data": {
    "common_examples": [
      {
        "text": "hey",
        "intent": "greet",
        "entities": []
      },
      {
        "text": "howdy",
        "intent": "greet",
        "entities": []
      },
      {
        "text": "hey there",
        "intent": "greet",
        "entities": []
      },
      {
        "text": "hello",
        "intent": "greet",
        "entities": []
      },
      {
        "text": "hi",
        "intent": "greet",
        "entities": []
      },
      {
        "text": "good morning",
        "intent": "greet",
        "entities": []
      },
      {
        "text": "good evening",
        "intent": "greet",
        "entities": []
      },
      {
        "text": "dear sir",
        "intent": "greet",
        "entities": []
      },
      {
        "text": "where should I start my sightseeing in berlin?",
        "intent": "inform",
        "entities": [
          {
            "start": 39,
            "end": 45,
            "value": "berlin",
            "entity": "location"
          }
        ]
      },
      {
        "text": "what is the popular park in berlin?",
        "intent": "inform",
        "entities": [
          {
            "start": 20,
            "end": 24,
            "value": "park",
            "entity": "type_specific"
          },
          {
            "start": 28,
            "end": 34,
            "value": "berlin",
            "entity": "location"
          }
        ]
      },
      {
        "text": "what is the famous museum in berlin?",
        "intent": "inform",
        "entities": [
          {
            "start": 19,
            "end": 25,
            "value": "museum",
            "entity": "type_specific"
          },
          {
            "start": 29,
            "end": 35,
            "value": "berlin",
            "entity": "location"
          }
        ]
      },
      {
        "text": "what is the famous park?",
        "intent": "inform",
        "entities": [
          {
            "start": 19,
            "end": 23,
            "value": "park",
            "entity": "type_specific"
          }
        ]
      },
      {
        "text": "what is the popular museum?",
        "intent": "inform",
        "entities": [
          {
            "start": 20,
            "end": 26,
            "value": "museum",
            "entity": "type_specific"
          }
        ]
      },
      {
        "text": "i need some recommendations for indoor places in berlin",
        "intent": "inform",
        "entities": [
          {
            "start": 32,
            "end": 38,
            "value": "indoor",
            "entity": "type"
          },
          {
            "start": 49,
            "end": 55,
            "value": "berlin",
            "entity": "location"
          }
        ]
      },
      {
        "text": "i need some recommendations for outdoor places in berlin",
        "intent": "inform",
        "entities": [
          {
            "start": 32,
            "end": 39,
            "value": "outdoor",
            "entity": "type"
          },
          {
            "start": 50,
            "end": 56,
            "value": "berlin",
            "entity": "location"
          }
        ]
      },
      {
        "text": "i need some recommendations for outdoor places",
        "intent": "inform",
        "entities": [
          {
            "start": 32,
            "end": 39,
            "value": "outdoor",
            "entity": "type"
          }
        ]
      },
      {
        "text": "i need some recommendations for indoor places",
        "intent": "inform",
        "entities": [
          {
            "start": 32,
            "end": 38,
            "value": "indoor",
            "entity": "type"
          }
        ]
      },
      {
        "text": "in berlin",
        "intent": "inform",
        "entities": [
          {
            "start": 3,
            "end": 9,
            "value": "berlin",
            "entity": "location"
          }
        ]
      },
      {
        "text": "cheap",
        "intent": "inform",
        "entities": [
          {
            "start": 0,
            "end": 5,
            "value": "cheap",
            "entity": "price"
          }
        ]
      },
      {
        "text": "moderately cheap",
        "intent": "inform",
        "entities": [
          {
            "start": 0,
            "end": 16,
            "value": "moderately cheap",
            "entity": "price"
          }
        ]
      },
      {
        "text": "moderately expensive",
        "intent": "inform",
        "entities": [
          {
            "start": 0,
            "end": 20,
            "value": "moderately expensive",
            "entity": "price"
          }
        ]
      },
      {
        "text": "expensive",
        "intent": "inform",
        "entities": [
          {
            "start": 0,
            "end": 9,
            "value": "expensive",
            "entity": "price"
          }
        ]
      },
      {
        "text": "can you recommend somewhere else?",
        "intent": "deny",
        "entities": []
      },
      {
        "text": "can you suggest another place?",
        "intent": "deny",
        "entities": []
      },
      {
        "text": "great!",
        "intent": "affirm",
        "entities": []
      },
      {
        "text": "that sounds like a great plan",
        "intent": "affirm",
        "entities": []
      },
      {
        "text": "thank you",
        "intent": "thankyou",
        "entities": []
      },
      {
        "text": "thanks",
        "intent": "thankyou",
        "entities": []
      },
      {
        "text": "no thank you",
        "intent": "deny",
        "entities": []
      },
      {
        "text": "no thanks",
        "intent": "deny",
        "entities": []
      },
      {
        "text": "no",
        "intent": "deny",
        "entities": []
      },
      {
        "text": "when is it opened?",
        "intent": "request_info",
        "entities": [
          {
            "start": 11,
            "end": 17,
            "value": "opening time",
            "entity": "info"
          }
        ]
      },
      {
        "text": "what is its address?",
        "intent": "request_info",
        "entities": [
          {
            "start": 12,
            "end": 19,
            "value": "address",
            "entity": "info"
          }
        ]
      },
      {
        "text": "what is its phone number?",
        "intent": "request_info",
        "entities": [
          {
            "start": 12,
            "end": 24,
            "value": "phone num",
            "entity": "info"
          }
        ]
      },
      {
        "text": "what is its opening time?",
        "intent": "request_info",
        "entities": [
          {
            "start": 12,
            "end": 24,
            "value": "opening time",
            "entity": "info"
          }
        ]
      },
      {
        "text": "what is its closing time?",
        "intent": "request_info",
        "entities": [
          {
            "start": 12,
            "end": 24,
            "value": "closing time",
            "entity": "info"
          }
        ]
      },
      {
        "text": "where is it",
        "intent": "request_info",
        "entities": [
          {
            "start": 0,
            "end": 5,
            "value": "address",
            "entity": "info"
          }
        ]
      },
      {
        "text": "what's its rating?",
        "intent": "request_info",
        "entities": [
          {
            "start": 11,
            "end": 17,
            "value": "rating",
            "entity": "info"
          }
        ]
      },
      {
        "text": "how is it rated?",
        "intent": "request_info",
        "entities": [
          {
            "start": 10,
            "end": 15,
            "value": "rating",
            "entity": "info"
          }
        ]
      },
      {
        "text": "sounds good",
        "intent": "affirm",
        "entities": []
      },
      {
        "text": "nice i like it",
        "intent": "affirm",
        "entities": []
      },
      {
        "text": "no thanks",
        "intent": "deny",
        "entities": []
      },
      {
        "text": "yes",
        "intent": "affirm",
        "entities": []
      },
      {
        "text": "what is the best place to visit in new york",
        "intent": "inform",
        "entities": [
          {
            "start": 35,
            "end": 43,
            "value": "new york",
            "entity": "location"
          }
        ]
      },
      {
        "text": "I like this brandemburger gate",
        "intent": "affirm",
        "entities": []
      },
      {
        "text": "i like this eiffel tower",
        "intent": "affirm",
        "entities": []
      },
      {
        "text": "i don't like it",
        "intent": "deny",
        "entities": []
      },
      {
        "text": "i don't like it. can you recommend something else?",
        "intent": "deny",
        "entities": []
      },
      {
        "text": "next",
        "intent": "deny",
        "entities": []
      },
      {
        "text": "i don't fancy it",
        "intent": "deny",
        "entities": []
      },
      {
        "text": "give me another suggestion",
        "intent": "deny",
        "entities": []
      },
      {
        "text": "this museum is cool",
        "intent": "affirm",
        "entities": []
      },
      {
        "text": "i will visit this",
        "intent": "affirm",
        "entities": []
      },
      {
        "text": "i would like to visit an outdoor attraction in basel",
        "intent": "inform",
        "entities": [
          {
            "start": 47,
            "end": 52,
            "value": "basel",
            "entity": "location"
          },
          {
            "start": 25,
            "end": 32,
            "value": "outdoor",
            "entity": "type"
          }
        ]
      },
      {
        "text": "can you recommend me a museum in berlin?",
        "intent": "inform",
        "entities": [
          {
            "start": 33,
            "end": 39,
            "value": "berlin",
            "entity": "location"
          },
          {
            "start": 23,
            "end": 29,
            "value": "museum",
            "entity": "type_specific"
          }
        ]
      },
      {
        "text": "what is the best palace in berlin?",
        "intent": "inform",
        "entities": [
          {
            "start": 27,
            "end": 33,
            "value": "berlin",
            "entity": "location"
          },
          {
            "start": 17,
            "end": 23,
            "value": "palace",
            "entity": "type_specific"
          }
        ]
      }
    ]
  }
}